{
    "caption": "a sticker of a cartoon open box a creative illustrated sticker of a cartoon open box stock illustration",
    "url": "https://thumbs.dreamstime.com/b/sticker-quirky-hand-drawn-cartoon-open-box-creative-illustrated-147705402.jpg",
    "key": "000049292",
    "status": "success",
    "error_message": null,
    "width": 256,
    "height": 256,
    "original_width": 800,
    "original_height": 800,
    "exif": "{}",
    "sha256": "4e8017d6f2e7bdcf22300fb6b5db65d8b015bb4bc1f8f7f1d6c016ee9a6f8dd9"
}