{
    "caption": "the wooden cupboard with plants in the corner and a mirror above it",
    "url": "https://img.rawpixel.com/s3fs-private/rawpixel_images/website_content/p-386-felix-8681-card.jpg?w=800&dpr=1&fit=default&crop=default&auto=format&fm=pjpg&q=75&vib=3&con=3&usm=15&bg=F4F4F3&ixlib=js-2.2.1&s=f65d7caf6db4f587c99fe602849115f9",
    "key": "000049297",
    "status": "success",
    "error_message": null,
    "width": 256,
    "height": 256,
    "original_width": 800,
    "original_height": 533,
    "exif": "{}",
    "sha256": "e2a0b7bcf532c48fac6e755408c78790936c077be681632a89b9fd210bb87086"
}