{
    "caption": "a statue stands in front",
    "url": "https://www.tsemrinpoche.com/wp-content/uploads/2018/02/Gandhi033.jpg",
    "key": "000047762",
    "status": "success",
    "error_message": null,
    "width": 256,
    "height": 256,
    "original_width": 4128,
    "original_height": 2944,
    "exif": "{\"Image Make\": \"Canon\", \"Image Model\": \"Canon EOS 5D Mark II\", \"Image Orientation\": \"Horizontal (normal)\", \"Image XResolution\": \"240\", \"Image YResolution\": \"240\", \"Image ResolutionUnit\": \"Pixels/Inch\", \"Image Software\": \"Adobe Photoshop CS6 (Windows)\", \"Image DateTime\": \"2015:04:05 19:48:08\", \"Image ExifOffset\": \"216\", \"Thumbnail Compression\": \"JPEG (old-style)\", \"Thumbnail XResolution\": \"72\", \"Thumbnail YResolution\": \"72\", \"Thumbnail ResolutionUnit\": \"Pixels/Inch\", \"Thumbnail JPEGInterchangeFormat\": \"850\", \"Thumbnail JPEGInterchangeFormatLength\": \"3732\", \"EXIF ExposureTime\": \"1/30\", \"EXIF FNumber\": \"16/5\", \"EXIF ExposureProgram\": \"Manual\", \"EXIF ISOSpeedRatings\": \"1000\", \"EXIF ExifVersion\": \"\", \"EXIF DateTimeOriginal\": \"2015:04:04 22:10:18\", \"EXIF DateTimeDigitized\": \"2015:04:04 22:10:18\", \"EXIF ShutterSpeedValue\": \"4906891/1000000\", \"EXIF ApertureValue\": \"209759/62500\", \"EXIF ExposureBiasValue\": \"0\", \"EXIF MaxApertureValue\": \"3\", \"EXIF MeteringMode\": \"Pattern\", \"EXIF Flash\": \"Flash did not fire, compulsory flash mode\", \"EXIF FocalLength\": \"20\", \"EXIF SubSecTime\": \"48\", \"EXIF SubSecTimeOriginal\": \"48\", \"EXIF SubSecTimeDigitized\": \"48\", \"EXIF ColorSpace\": \"Uncalibrated\", \"EXIF ExifImageWidth\": \"4128\", \"EXIF ExifImageLength\": \"2944\", \"EXIF FocalPlaneXResolution\": \"5616000/1459\", \"EXIF FocalPlaneYResolution\": \"1872000/479\", \"EXIF FocalPlaneResolutionUnit\": \"2\", \"EXIF CustomRendered\": \"Normal\", \"EXIF ExposureMode\": \"Manual Exposure\", \"EXIF WhiteBalance\": \"Manual\", \"EXIF SceneCaptureType\": \"Standard\", \"EXIF BodySerialNumber\": \"332345536\", \"EXIF LensSpecification\": \"[20, 20, 0/0, 0/0]\", \"EXIF LensModel\": \"EF20mm f/2.8 USM\"}",
    "sha256": "438452c392ffaa7522c245b7d2426bd9438654bda69ce38db006203ca0ad8497"
}