{
    "caption": "a red and white checkered dog bandana with a white button, on a white background",
    "url": "https://cdn.shopify.com/s/files/1/1800/4707/products/BP-0069_1024x1024.jpg?v=1578686036",
    "key": "000042845",
    "status": "success",
    "error_message": null,
    "width": 256,
    "height": 256,
    "original_width": 750,
    "original_height": 750,
    "exif": "{\"Image Orientation\": \"Horizontal (normal)\", \"Image XResolution\": \"350\", \"Image YResolution\": \"350\", \"Image ResolutionUnit\": \"Pixels/Inch\", \"Image YCbCrPositioning\": \"Centered\", \"Image ExifOffset\": \"102\", \"EXIF ExifVersion\": \"\", \"EXIF ComponentsConfiguration\": \"\", \"EXIF FlashPixVersion\": \"\", \"EXIF ColorSpace\": \"Uncalibrated\", \"EXIF ExifImageWidth\": \"750\", \"EXIF ExifImageLength\": \"750\"}",
    "sha256": "78e8ef8022b05fd510b0a33fb02082f4513ca86fda1186e2b1f00f24fc507b9d"
}