{
    "caption": "a cartoon illustration of a elf in love",
    "url": "https://us.123rf.com/450wm/cthoman/cthoman1805/cthoman180502180/101916063-stock-vector-a-cartoon-robin-hood-ready-to-give-a-hug-.jpg?ver=6",
    "key": "000041266",
    "status": "success",
    "error_message": null,
    "width": 256,
    "height": 256,
    "original_width": 438,
    "original_height": 450,
    "exif": "{\"Image ImageDescription\": \"A cartoon Robin Hood ready to give a hug.\", \"Image Orientation\": \"Horizontal (normal)\", \"Image XResolution\": \"300\", \"Image YResolution\": \"300\", \"Image ResolutionUnit\": \"Pixels/Inch\", \"Image Software\": \"Adobe Photoshop CC 2017 (Macintosh)\", \"Image DateTime\": \"2017:10:05 10:36:54\", \"Image ExifOffset\": \"224\", \"Thumbnail Compression\": \"JPEG (old-style)\", \"Thumbnail XResolution\": \"300\", \"Thumbnail YResolution\": \"300\", \"Thumbnail ResolutionUnit\": \"Pixels/Inch\", \"Thumbnail JPEGInterchangeFormat\": \"374\", \"Thumbnail JPEGInterchangeFormatLength\": \"6365\", \"EXIF ExifVersion\": \"\", \"EXIF ColorSpace\": \"sRGB\", \"EXIF ExifImageWidth\": \"3000\", \"EXIF ExifImageLength\": \"3079\"}",
    "sha256": "51794f4bb8637a8ea22fff29698dcd8999ce6cffe0fe4a2305934caa1068e0e4"
}