{
    "caption": "an ink drawing of a robot from a series of experiments",
    "url": "https://ksr-ugc.imgix.net/assets/019/766/796/4bf53250b9f7b5c3b59943b6b03a5f68_original.jpg?ixlib=rb-2.1.0&w=680&fit=max&v=1515082845&auto=format&frame=1&q=92&s=a1c7990f95a4cb12f5ecb93e8c3ae6d0",
    "key": "000040313",
    "status": "success",
    "error_message": null,
    "width": 256,
    "height": 256,
    "original_width": 680,
    "original_height": 510,
    "exif": "{}",
    "sha256": "6b396c5224d5a6350e464e50b76dd9f958b778d13873f9a6e28d307c639d0b50"
}