{
    "caption": "an alien is flying through a black hole that looks like the truth is out there classic t shirt",
    "url": "https://ih1.redbubble.net/image.209737603.4217/ssrco,classic_tee,womens,101010:01c5ca27c6,front,square_product,x600-bg,f8f8f8.1u10.jpg",
    "key": "000042508",
    "status": "success",
    "error_message": null,
    "width": 256,
    "height": 256,
    "original_width": 600,
    "original_height": 600,
    "exif": "{}",
    "sha256": "ef0efe9f756f5ee323efbf839e184af20a94a16e5134883da48fe92fc5167bf0"
}