{
    "caption": "an elephant drawing",
    "url": "http://cdn.shopify.com/s/files/1/0101/2488/6075/products/Elephant_3_x_16_1200x1200.jpg?v=1543363172",
    "key": "000042169",
    "status": "success",
    "error_message": null,
    "width": 256,
    "height": 256,
    "original_width": 792,
    "original_height": 975,
    "exif": "{\"Image Orientation\": \"Horizontal (normal)\", \"Image XResolution\": \"72\", \"Image YResolution\": \"72\", \"Image ResolutionUnit\": \"Pixels/Inch\", \"Image YCbCrPositioning\": \"Centered\", \"Image ExifOffset\": \"102\", \"EXIF ExifVersion\": \"\", \"EXIF ComponentsConfiguration\": \"\", \"EXIF FlashPixVersion\": \"\", \"EXIF ColorSpace\": \"Uncalibrated\", \"EXIF ExifImageWidth\": \"792\", \"EXIF ExifImageLength\": \"975\"}",
    "sha256": "72bd0c3029a3154638c66662dacb49698ef7aa76d6f513b6d6fe7c495b2b376e"
}