{
    "caption": "a woman smiling at the camera",
    "url": "https://www.baltimoresun.com/resizer/zkAqqrfFpxfN5vhSTGzWWpcYXOA=/fit-in/800x533/smart/filters:fill(black)/arc-anglerfish-arc2-prod-tronc.s3.amazonaws.com/public/QVEQMXX2NZCTRNPJZDD7HUNQL4.jpg",
    "key": "000049346",
    "status": "success",
    "error_message": null,
    "width": 256,
    "height": 256,
    "original_width": 800,
    "original_height": 533,
    "exif": "{}",
    "sha256": "336fd479182804196a709e581af7920f05b7c1d2290b3d87e363e4d59561ecd7"
}