{
    "caption": "a woman hugging two girls on a couch",
    "url": "https://imagesvc.meredithcorp.io/v3/mm/image?url=https%3A%2F%2Fstatic.onecms.io%2Fwp-content%2Fuploads%2Fsites%2F38%2F2020%2F04%2F08%2FRMRM1_12_KL_screenshot.jpg",
    "key": "000043461",
    "status": "success",
    "error_message": null,
    "width": 256,
    "height": 256,
    "original_width": 1500,
    "original_height": 844,
    "exif": "{}",
    "sha256": "ca5d84e1d1185c73ae239882a8e2441fd0e9ffe166f8ef11c20de761eece2ab0"
}