{
    "caption": "an old car interior with red leather seats",
    "url": "https://render.fineartamerica.com/images/rendered/default/greeting-card/images/artworkimages/medium/1/interior-of-a-classic-american-car-sami-sarkis.jpg?&targetx=-23&targety=0&imagewidth=747&imageheight=500&modelwidth=700&modelheight=500&backgroundcolor=161615&orientation=0",
    "key": "000042895",
    "status": "success",
    "error_message": null,
    "width": 256,
    "height": 256,
    "original_width": 700,
    "original_height": 500,
    "exif": "{}",
    "sha256": "dc227caf01312032ad8b7079d18eee237bd0852bd416bfd26a1335a10a46dd0e"
}