{
    "caption": "the single bedroom in the home",
    "url": "https://img.rentberry.com/9JFucb4aZYViUTQn6hqXxD-ZnJxaAf82HhLZJ9CHpnk/auto/440/440/sm/1/plain/media/apartments/29d888b0-3db4-11ea-8c75-6ee10a576987.jpeg",
    "key": "000029550",
    "status": "success",
    "error_message": null,
    "width": 256,
    "height": 256,
    "original_width": 440,
    "original_height": 440,
    "exif": "{\"Image Orientation\": \"Horizontal (normal)\", \"Image XResolution\": \"72\", \"Image YResolution\": \"72\", \"Image ResolutionUnit\": \"Pixels/Inch\", \"Image YCbCrPositioning\": \"Centered\", \"Image ExifOffset\": \"102\", \"EXIF ExifVersion\": \"\", \"EXIF ComponentsConfiguration\": \"\", \"EXIF FlashPixVersion\": \"\", \"EXIF ColorSpace\": \"Uncalibrated\", \"EXIF ExifImageWidth\": \"440\", \"EXIF ExifImageLength\": \"440\"}",
    "sha256": "a3e176627ef993ed967976121f6fd40684dab01bbe0d626ff250aa555134e19a"
}