{
    "caption": "brass statues on a market in chennai india, an art fair held for children to sell on the street and",
    "url": "https://thumbs.dreamstime.com/b/bronze-idols-goddess-lakshmi-antique-finish-hindu-wealth-auspiciousness-166372124.jpg",
    "key": "000023832",
    "status": "success",
    "error_message": null,
    "width": 256,
    "height": 256,
    "original_width": 800,
    "original_height": 533,
    "exif": "{}",
    "sha256": "b08cd6e685ec323dcaf35e35f0f15f0eda84ac094ebfc3bd574b50dff7421012"
}