{
    "caption": "person attends the european premiere of creed on november 1 2017 in london england",
    "url": "https://media.gettyimages.com/photos/niamh-mcgrady-attends-the-uk-premiere-of-fifty-shades-darker-at-odeon-picture-id634410818?s=612x612",
    "key": "000020385",
    "status": "success",
    "error_message": null,
    "width": 256,
    "height": 256,
    "original_width": 420,
    "original_height": 612,
    "exif": "{\"Image ImageDescription\": \"LONDON, ENGLAND - FEBRUARY 09:  Niamh McGrady attends the UK Premiere of \\\"Fifty Shades Darker\\\" at Odeon Leicester Square on February 9, 2017 in London, United Kingdom.  (Photo by David M. Benett/Dave Benett/WireImage)\", \"Image Copyright\": \"2017 David M. Benett\"}",
    "sha256": "bd4e804c0e860a36a06a4c140a79ef1695d3b94768fb715615a4e27844bd5d00"
}