{
    "caption": "an acrylic painting of a classic motorbike on the beach",
    "url": "https://render.fineartamerica.com/images/rendered/default/flatrolled/yoga-mat/images-medium-5/henderson-art-deco-luke-karcz.jpg?&targetx=0&targety=-216&imagewidth=1320&imageheight=873&modelwidth=1320&modelheight=440&backgroundcolor=D7CAB3&orientation=1&producttype=yogamat",
    "key": "000023784",
    "status": "success",
    "error_message": null,
    "width": 256,
    "height": 256,
    "original_width": 1171,
    "original_height": 500,
    "exif": "{}",
    "sha256": "b065bc6d72d86d69b3a6ea40ad25abcec591aa4a04ea381de120382ea5a00de1"
}