{
    "caption": "an aerial view of the sprawling skyline of cairo taken from a high rise tower in the egyptian capital",
    "url": "https://media.gettyimages.com/photos/the-city-of-cairo-aerial-view-of-downtown-in-cairo-on-september-21-picture-id872389694?s=612x612",
    "key": "000029584",
    "status": "success",
    "error_message": null,
    "width": 256,
    "height": 256,
    "original_width": 612,
    "original_height": 408,
    "exif": "{\"Image ImageDescription\": \"CAIRO, EGYPT - SEPTEMBER 21 : The city of Cairo. Aerial view of downtown in Cairo on September 21, 2014 in Cairo, Egypt. (Photo by Fr?d?ric Soltan/Corbis via Getty Images)\", \"Image Copyright\": \"2017 Fr?d?ric Soltan\"}",
    "sha256": "761702e4e2f65ad019f34bd7e4d599e3c3d5f3aa0d8162236edb5650a0dd1431"
}