{
    "caption": "the river that runs through the mountains, with the water running down it",
    "url": "http://www.listeningearth.com.au/blog_images/2010_05/BSC_03.jpg",
    "key": "000019966",
    "status": "success",
    "error_message": null,
    "width": 256,
    "height": 256,
    "original_width": 1000,
    "original_height": 667,
    "exif": "{\"Image Make\": \"Canon\", \"Image Model\": \"Canon EOS 30D\", \"Image Orientation\": \"Horizontal (normal)\", \"Image XResolution\": \"72\", \"Image YResolution\": \"72\", \"Image ResolutionUnit\": \"Pixels/Inch\", \"Image DateTime\": \"2010:05:05 17:58:58\", \"Image YCbCrPositioning\": \"Co-sited\", \"Image ExifOffset\": \"5674\", \"Thumbnail ImageWidth\": \"200\", \"Thumbnail ImageLength\": \"133\", \"Thumbnail Compression\": \"JPEG (old-style)\", \"Thumbnail Orientation\": \"Horizontal (normal)\", \"Thumbnail JPEGInterchangeFormat\": \"168\", \"Thumbnail JPEGInterchangeFormatLength\": \"5391\", \"EXIF ExposureTime\": \"4\", \"EXIF FNumber\": \"22\", \"EXIF ExposureProgram\": \"Aperture Priority\", \"EXIF ISOSpeedRatings\": \"100\", \"EXIF ExifVersion\": \"\", \"EXIF DateTimeOriginal\": \"2010:05:05 17:58:58\", \"EXIF DateTimeDigitized\": \"2010:05:05 17:58:58\", \"EXIF ComponentsConfiguration\": \"\", \"EXIF ShutterSpeedValue\": \"-131071/65536\", \"EXIF ApertureValue\": \"584507/65536\", \"EXIF ExposureBiasValue\": \"-4/3\", \"EXIF MeteringMode\": \"Pattern\", \"EXIF Flash\": \"Flash did not fire, compulsory flash mode\", \"EXIF FocalLength\": \"21\", \"EXIF FlashPixVersion\": \"\", \"EXIF ColorSpace\": \"sRGB\", \"EXIF ExifImageWidth\": \"1000\", \"EXIF ExifImageLength\": \"667\", \"Interoperability InteroperabilityIndex\": \"R98\", \"Interoperability InteroperabilityVersion\": \"[0, 0, 0, 0]\", \"EXIF InteroperabilityOffset\": \"5992\", \"EXIF FocalPlaneXResolution\": \"233600/59\", \"EXIF FocalPlaneYResolution\": \"233600/59\", \"EXIF FocalPlaneResolutionUnit\": \"2\", \"EXIF CustomRendered\": \"Normal\", \"EXIF ExposureMode\": \"Auto Exposure\", \"EXIF WhiteBalance\": \"Auto\", \"EXIF SceneCaptureType\": \"Standard\"}",
    "sha256": "c543a51c832af5112fa1aea9317c9d7b7380d54f624539652a46c0fca32d6447"
}