{
    "caption": "an image of a photo with a tree imprint on it",
    "url": "https://cdn.shopify.com/s/files/1/0044/3233/0865/products/10_32232d27-5222-4973-b987-fd04a25094ed_grande.jpg?v=1540576108",
    "key": "000012414",
    "status": "success",
    "error_message": null,
    "width": 256,
    "height": 256,
    "original_width": 600,
    "original_height": 450,
    "exif": "{\"Image Orientation\": \"Horizontal (normal)\", \"Image XResolution\": \"96\", \"Image YResolution\": \"96\", \"Image ResolutionUnit\": \"Pixels/Inch\", \"Image YCbCrPositioning\": \"Centered\", \"Image ExifOffset\": \"102\", \"EXIF ExifVersion\": \"\", \"EXIF ComponentsConfiguration\": \"\", \"EXIF FlashPixVersion\": \"\", \"EXIF ColorSpace\": \"Uncalibrated\", \"EXIF ExifImageWidth\": \"600\", \"EXIF ExifImageLength\": \"450\"}",
    "sha256": "5a70726725658ae3a35bf94935cf80c96ae8e42cdcb075eae61431c62b36d2b0"
}