{
    "caption": "the bathroom at the hospital with neon lights",
    "url": "https://a57.foxnews.com/a57.foxnews.com/static.foxnews.com/foxnews.com/content/uploads/2018/09/640/320/1862/1048/blue_light_bathroom.jpg?ve=1&tl=1?ve=1&tl=1",
    "key": "000019769",
    "status": "success",
    "error_message": null,
    "width": 256,
    "height": 256,
    "original_width": 1862,
    "original_height": 1048,
    "exif": "{}",
    "sha256": "66659cab5e49d5cc0d0c9d22714b7e26fbf583c27133b0de8b1fa7b7d3a213a2"
}