{
    "caption": "a woman takes pictures with her camera near the ocean",
    "url": "https://i1.adis.ws/i/canon/canon_eos_111-2c9155da-3f32-11ea-8587-1c4d704464ac?w=1200&sm=aspect&aspect=16:9&qlt=70&fmt=jpg&fmt.options=interlaced&fmt=jpg&fmt.options=interlaced&bg=rgb(255,255,255)",
    "key": "000019726",
    "status": "success",
    "error_message": null,
    "width": 256,
    "height": 256,
    "original_width": 1200,
    "original_height": 675,
    "exif": "{}",
    "sha256": "82f59fc8e4a59c45cf6d0fafbd1cf2523d375f7806cdd3a8ab8e22e3a87cdf98"
}