{
    "caption": "a lunch plate with tater tots, cheese fries, and coleslaw",
    "url": "https://static1.squarespace.com/static/52851d10e4b0089d8e2f902b/528e59f5e4b0a636d24cb388/5592d0e7e4b05f65867ac510/1542336323943/?format=1500w",
    "key": "000017612",
    "status": "success",
    "error_message": null,
    "width": 256,
    "height": 256,
    "original_width": 1200,
    "original_height": 1600,
    "exif": "{\"Image Make\": \"Apple\", \"Image Model\": \"iPhone 3G\", \"Image Orientation\": \"Horizontal (normal)\", \"Image XResolution\": \"72\", \"Image YResolution\": \"72\", \"Image ResolutionUnit\": \"Pixels/Inch\", \"Image Software\": \"QuickTime 7.6.6\", \"Image DateTime\": \"2010:05:01 20:43:36\", \"Image HostComputer\": \"Mac OS X 10.5.8\", \"Image YCbCrPositioning\": \"Centered\", \"Image ExifOffset\": \"254\", \"GPS GPSLatitudeRef\": \"N\", \"GPS GPSLatitude\": \"[41, 517/25, 0]\", \"GPS GPSLongitudeRef\": \"W\", \"GPS GPSLongitude\": \"[72, 48/25, 0]\", \"GPS GPSTimeStamp\": \"[11, 43, 911/100]\", \"Image GPSInfo\": \"508\", \"Thumbnail Compression\": \"JPEG (old-style)\", \"Thumbnail XResolution\": \"72\", \"Thumbnail YResolution\": \"72\", \"Thumbnail ResolutionUnit\": \"Pixels/Inch\", \"Thumbnail JPEGInterchangeFormat\": \"752\", \"Thumbnail JPEGInterchangeFormatLength\": \"5496\", \"Thumbnail YCbCrPositioning\": \"Centered\", \"EXIF FNumber\": \"14/5\", \"EXIF ExposureProgram\": \"Program Normal\", \"EXIF ExifVersion\": \"\", \"EXIF DateTimeOriginal\": \"2010:04:19 11:43:13\", \"EXIF DateTimeDigitized\": \"2010:04:19 11:43:13\", \"EXIF ComponentsConfiguration\": \"\", \"EXIF ApertureValue\": \"4281/1441\", \"EXIF MeteringMode\": \"Average\", \"EXIF Flash\": \"No flash function\", \"EXIF FlashPixVersion\": \"\", \"EXIF ColorSpace\": \"sRGB\", \"EXIF ExifImageWidth\": \"1600\", \"EXIF ExifImageLength\": \"1200\", \"EXIF SensingMethod\": \"One-chip color area\", \"EXIF ExposureMode\": \"Auto Exposure\", \"EXIF WhiteBalance\": \"Auto\"}",
    "sha256": "d7d57b88d9c4993cd17d9a49f61649579f6ef83f87060f30b6ce2a5576c52a0a"
}