{
    "caption": "the red tears tear pendant",
    "url": "https://cdn.shopify.com/s/files/1/0026/1016/7908/products/8__sparkle-all-the-way-pink__qty-3__2_1024x.jpg?v=1566945025",
    "key": "000012905",
    "status": "success",
    "error_message": null,
    "width": 256,
    "height": 256,
    "original_width": 1000,
    "original_height": 1500,
    "exif": "{\"Image Orientation\": \"Horizontal (normal)\", \"Image XResolution\": \"72\", \"Image YResolution\": \"72\", \"Image ResolutionUnit\": \"Pixels/Inch\", \"Image YCbCrPositioning\": \"Centered\", \"Image ExifOffset\": \"102\", \"EXIF ExifVersion\": \"\", \"EXIF ComponentsConfiguration\": \"\", \"EXIF FlashPixVersion\": \"\", \"EXIF ColorSpace\": \"Uncalibrated\", \"EXIF ExifImageWidth\": \"1000\", \"EXIF ExifImageLength\": \"1500\"}",
    "sha256": "5fc859cb7295efa45be10e07b78e0b60dd3655c4bbb142a3c6bce8d58530e8c8"
}