{
    "caption": "the great kapok tree",
    "url": "https://1.bp.blogspot.com/-5VLFbBsUQZY/U9FKEtHBUsI/AAAAAAAABdc/jgAo0B5ytKA/s1600/61FWyx4YeIL.jpg",
    "key": "000019512",
    "status": "success",
    "error_message": null,
    "width": 256,
    "height": 256,
    "original_width": 416,
    "original_height": 500,
    "exif": "{\"Image Software\": \"Google\", \"Image ExifOffset\": \"46\", \"EXIF ExifVersion\": \"\", \"EXIF ColorSpace\": \"sRGB\", \"Interoperability InteroperabilityIndex\": \"R98\", \"Interoperability InteroperabilityVersion\": \"[0, 0, 0, 0]\", \"EXIF InteroperabilityOffset\": \"88\"}",
    "sha256": "39f2204eca92a407b04368306abde355c1ac63cb7bacd984e2d3269a897cd861"
}