{
    "caption": "a single daisy is sitting on the grass and looking around",
    "url": "https://media.gettyimages.com/photos/chamomile-flower-on-grass-field-picture-id649380508?b=1&k=6&m=649380508&s=612x612&w=0&h=gGLuC9mN3vrihlnQ7Dxqmc4AZ1GBqbEHhE0srrR9Xtw=",
    "key": "000019934",
    "status": "success",
    "error_message": null,
    "width": 256,
    "height": 256,
    "original_width": 612,
    "original_height": 408,
    "exif": "{\"Image ImageDescription\": \"Chamomile flower on grass field on sunny summer day. View with copy space\"}",
    "sha256": "155ce009e6dc723aedccca65bb35a6998a0b9abd9837e658c00242996266e2f0"
}