{
    "caption": "blue mask on yellow background",
    "url": "https://img.rawpixel.com/s3fs-private/rawpixel_images/website_content/pf-s58-kut-4429-pom.jpg?w=800&dpr=1&fit=default&crop=default&auto=format&fm=pjpg&q=75&vib=3&con=3&usm=15&bg=F4F4F3&ixlib=js-2.2.1&s=ae5f8f83961ced1bce50c94f676fd576",
    "key": "000030315",
    "status": "success",
    "error_message": null,
    "width": 256,
    "height": 256,
    "original_width": 800,
    "original_height": 533,
    "exif": "{}",
    "sha256": "641db1cda601795b2f78d1e6415e50012612cce7d3d9b20be967e4ff3a6474af"
}