{
    "caption": "boys playing in a street in manchester, england, in this picture dated from august 21, 1932",
    "url": "https://media.gettyimages.com/photos/children-play-in-a-yard-with-the-gorbals-a-notorious-slum-area-of-picture-id613477122?s=612x612",
    "key": "000035894",
    "status": "success",
    "error_message": null,
    "width": 256,
    "height": 256,
    "original_width": 612,
    "original_height": 401,
    "exif": "{\"Image ImageDescription\": \"Children play in a yard with the 'Gorbals', a notorious slum area of Glasgow, January 1948. (Photo by ? Hulton-Deutsch Collection/CORBIS/Corbis via Getty Images)\"}",
    "sha256": "92d1e0994ae1be699354fb1e3c10c688994346bcf8a44f3223dff61c6e60fea1"
}