{
    "caption": "realistic monarch butterfly with puppies",
    "url": "https://media.istockphoto.com/vectors/set-of-butterfly-life-cycle-vector-id996985036?b=1&k=6&m=996985036&s=612x612&h=fGkV1Hn5w6s6L3fItS4qRqPrSyEsYji93pITN_wxnxk=",
    "key": "000033289",
    "status": "success",
    "error_message": null,
    "width": 256,
    "height": 256,
    "original_width": 612,
    "original_height": 537,
    "exif": "{\"Image ImageDescription\": \"A Set of Butterfly Life Cycle illustration\"}",
    "sha256": "1e5f508f7e9c26d59c78b21c88583135ebdbadcf8c4b3d6adf5584bb190f8022"
}