{
    "caption": "sunlight through trees in a deciduous forest",
    "url": "https://envato-shoebox-0.imgix.net/22d3/4f0f-809e-4b50-9f03-a57ec08c4bab/DSCF7167.jpg?auto=compress%2Cformat&fit=max&mark=https%3A%2F%2Felements-assets.envato.com%2Fstatic%2Fwatermark2.png&markalign=center%2Cmiddle&markalpha=18&w=700&s=fd24a95dcb999e7a5873fc9fd740301a",
    "key": "000032170",
    "status": "success",
    "error_message": null,
    "width": 256,
    "height": 256,
    "original_width": 700,
    "original_height": 467,
    "exif": "{}",
    "sha256": "98d8cb6dd6b7916bf7a3e1ebc1a1a4ff57fcdec776fc3baa66ed6241a274ae0f"
}