{
    "caption": "a bowl filled with tern chicken and rice",
    "url": "https://www.krumpli.co.uk/wp-content/uploads/2019/03/Sweet-and-Sour-Pork-Balls-5.jpg",
    "key": "000030778",
    "status": "success",
    "error_message": null,
    "width": 256,
    "height": 256,
    "original_width": 800,
    "original_height": 1200,
    "exif": "{\"Image Make\": \"Canon\", \"Image Model\": \"Canon EOS 70D\", \"Image Orientation\": \"Horizontal (normal)\", \"Image XResolution\": \"72\", \"Image YResolution\": \"72\", \"Image ResolutionUnit\": \"Pixels/Inch\", \"Image Software\": \"Adobe Photoshop Lightroom 6.1 (Windows)\", \"Image DateTime\": \"2019-03-11T12:43:03+01:00\", \"Image Artist\": \"BRIAN JONES\", \"Image Copyright\": \"BRIAN@BJONESPHOTOGRAPHY.CO.UK\", \"Image ExifOffset\": \"296\", \"EXIF ExposureTime\": \"1/200\", \"EXIF FNumber\": \"8\", \"EXIF ExposureProgram\": \"Manual\", \"EXIF ISOSpeedRatings\": \"100\", \"EXIF ExifVersion\": \"\", \"EXIF DateTimeOriginal\": \"2017:04:02 18:16:02\", \"EXIF DateTimeDigitized\": \"2017:04:02 18:16:02\", \"EXIF ShutterSpeedValue\": \"477741/62500\", \"EXIF ApertureValue\": \"6\", \"EXIF ExposureBiasValue\": \"0\", \"EXIF MaxApertureValue\": \"7/4\", \"EXIF MeteringMode\": \"CenterWeightedAverage\", \"EXIF Flash\": \"Flash did not fire, compulsory flash mode\", \"EXIF FocalLength\": \"50\", \"EXIF SubSecTimeOriginal\": \"62\", \"EXIF SubSecTimeDigitized\": \"62\", \"EXIF ExifImageWidth\": \"800\", \"EXIF ExifImageLength\": \"1200\", \"EXIF FocalPlaneXResolution\": \"5021939/2048\", \"EXIF FocalPlaneYResolution\": \"5021939/2048\", \"EXIF FocalPlaneResolutionUnit\": \"3\", \"EXIF ExposureMode\": \"Manual Exposure\", \"EXIF WhiteBalance\": \"Auto\", \"EXIF SceneCaptureType\": \"Standard\"}",
    "sha256": "bcf805c13312f5881958dc4b7fcfc39ce41d3ec1c413dac1dc850806ca90ab35"
}