{
    "caption": "the nrl queensland division building in townsville at the brisbane broncos stadium on july 23 2014 in brisbane australia",
    "url": "https://media.gettyimages.com/photos/general-view-of-rugby-league-central-the-home-of-the-nrl-during-a-nrl-picture-id451951756?s=612x612",
    "key": "000000146",
    "status": "success",
    "error_message": null,
    "width": 256,
    "height": 256,
    "original_width": 612,
    "original_height": 408,
    "exif": "{\"Image ImageDescription\": \"SYDNEY, AUSTRALIA - JULY 10:  A general view of Rugby League Central, the home of the NRL, during a NRL press conference at NRL Headquarters on July 10, 2014 in Sydney, Australia.  (Photo by Matt King/Getty Images)\", \"Image Copyright\": \"2014 Getty Images\"}",
    "sha256": "b09b46fbfc4f7390b7caf3a2e005603275428e9869b569624c9f3cab518a59ff"
}