{
    "caption": "a cartoon woman in a tattoo style portrait of an asian girl with the head in ears and the tail behind",
    "url": "https://image.shutterstock.com/image-vector/cartoon-girl-ponytail-colorful-cat-600w-723336433.jpg",
    "key": "000009913",
    "status": "success",
    "error_message": null,
    "width": 256,
    "height": 256,
    "original_width": 600,
    "original_height": 620,
    "exif": "{}",
    "sha256": "e98f47766174a4248d9f31fff7c8bcd8aaf11d2cfb4b267e79459b92078410d9"
}