{
    "caption": "the mandal art work is framed on the surface",
    "url": "https://cdn.shopify.com/s/files/1/0269/0459/2473/products/art-from-the-heart-nm-mandala-paintings-rainbow-mandala-sun-catcher-framed-rainbow-mandala-sun-catcher-mp1-13881548079193_500x.jpg?v=1587310814",
    "key": "000002813",
    "status": "success",
    "error_message": null,
    "width": 256,
    "height": 256,
    "original_width": 500,
    "original_height": 500,
    "exif": "{\"Image Orientation\": \"Horizontal (normal)\", \"Image XResolution\": \"72\", \"Image YResolution\": \"72\", \"Image ResolutionUnit\": \"Pixels/Inch\", \"Image YCbCrPositioning\": \"Centered\", \"Image ExifOffset\": \"102\", \"EXIF ExifVersion\": \"\", \"EXIF ComponentsConfiguration\": \"\", \"EXIF FlashPixVersion\": \"\", \"EXIF ColorSpace\": \"Uncalibrated\", \"EXIF ExifImageWidth\": \"500\", \"EXIF ExifImageLength\": \"500\"}",
    "sha256": "f1979299eeee7ead06ea50d78fb6eb3c9d0b3ca421f5a52a1abfd4a07cb0fdf2"
}