{
    "caption": "a black and white image of the newspaper front page with a newsprint",
    "url": "https://cdn.shopify.com/s/files/1/0249/9326/7772/products/7QAMSD019-01_600x.jpg?v=1574291426",
    "key": "000007700",
    "status": "success",
    "error_message": null,
    "width": 256,
    "height": 256,
    "original_width": 600,
    "original_height": 600,
    "exif": "{\"Image Orientation\": \"Horizontal (normal)\", \"Image XResolution\": \"72\", \"Image YResolution\": \"72\", \"Image ResolutionUnit\": \"Pixels/Inch\", \"Image YCbCrPositioning\": \"Centered\", \"Image ExifOffset\": \"102\", \"EXIF ExifVersion\": \"\", \"EXIF ComponentsConfiguration\": \"\", \"EXIF FlashPixVersion\": \"\", \"EXIF ColorSpace\": \"Uncalibrated\", \"EXIF ExifImageWidth\": \"600\", \"EXIF ExifImageLength\": \"600\"}",
    "sha256": "8df3b81ef6662cbed9b008e70f86c0188ade7b67037d5ff9381acdebd35beb7e"
}