{
    "caption": "text conversation about pregnant birth control",
    "url": "https://cf.girlsaskguys.com/q2628355/4586a977-2bec-4cc1-b8c4-5cff2602524a-m.jpg",
    "key": "000009949",
    "status": "success",
    "error_message": null,
    "width": 256,
    "height": 256,
    "original_width": 400,
    "original_height": 711,
    "exif": "{\"Image Orientation\": \"Horizontal (normal)\", \"Image ExifOffset\": \"38\", \"EXIF ExifImageWidth\": \"1242\", \"EXIF ExifImageLength\": \"2208\"}",
    "sha256": "ddf88c3af654893954e2f41aa02610820603fe2c3737f29d77d7f9941207617d"
}