{
    "caption": "a woman walking on her stomach wearing a blue yoga leggings",
    "url": "https://cdn.shopify.com/s/files/1/1824/3939/products/mockup-8b587e93_620x.jpg?v=1574647957",
    "key": "000008457",
    "status": "success",
    "error_message": null,
    "width": 256,
    "height": 256,
    "original_width": 620,
    "original_height": 620,
    "exif": "{\"Image Orientation\": \"Horizontal (normal)\", \"Image XResolution\": \"72\", \"Image YResolution\": \"72\", \"Image ResolutionUnit\": \"Pixels/Inch\", \"Image YCbCrPositioning\": \"Centered\", \"Image ExifOffset\": \"102\", \"EXIF ExifVersion\": \"\", \"EXIF ComponentsConfiguration\": \"\", \"EXIF FlashPixVersion\": \"\", \"EXIF ColorSpace\": \"Uncalibrated\", \"EXIF ExifImageWidth\": \"620\", \"EXIF ExifImageLength\": \"620\"}",
    "sha256": "942088bb1cfef56cd6313238e5063f0c5c257a57966e3c7ed4c0ccd41910ea6a"
}