{
    "caption": "a bear and her cub at the edge",
    "url": "http://1.bp.blogspot.com/-Ey1Ys8_-f_k/UI79GMNM_6I/AAAAAAAAYzw/8eDK2L98Iow/s640/DSCN9672-001.JPG",
    "key": "000000070",
    "status": "success",
    "error_message": null,
    "width": 256,
    "height": 256,
    "original_width": 640,
    "original_height": 480,
    "exif": "{\"Image Software\": \"Google\", \"Image Artist\": \"Picasa\", \"Image ExifOffset\": \"64\", \"EXIF ExifVersion\": \"\"}",
    "sha256": "e677219040950b510fb1db5d9fd7a65582b54bb6da23f5283879be7af0a928b5"
}