{
    "caption": "a tent with the rain fly off and no inside view",
    "url": "https://cdn10.bigcommerce.com/s-wyif3/products/168/images/2958/33__14093__37671.1525651971.1280.1280.jpg?c=2",
    "key": "000003148",
    "status": "success",
    "error_message": null,
    "width": 256,
    "height": 256,
    "original_width": 1280,
    "original_height": 1280,
    "exif": "{\"Image Orientation\": \"Horizontal (normal)\"}",
    "sha256": "cfa32f4e8d6f3f139c71320ff52a50cb759e906ea5e96ecf68f1e8054975fcba"
}